pychado/__init__.py
pychado/chado_tools.py
pychado/dbutils.py
pychado/ddl.py
pychado/queries.py
pychado/tasks.py
pychado/utils.py
pychado/data/defaultDatabase.yml
pychado/data/factorySettings.yml
pychado/data/gmodSchema.yml
pychado/io/__init__.py
pychado/io/direct.py
pychado/io/essentials.py
pychado/io/experiment.py
pychado/io/fasta.py
pychado/io/gaf.py
pychado/io/gaf2.py
pychado/io/gff.py
pychado/io/iobase.py
pychado/io/ontology.py
pychado/orm/__init__.py
pychado/orm/audit.py
pychado/orm/base.py
pychado/orm/companalysis.py
pychado/orm/cv.py
pychado/orm/general.py
pychado/orm/organism.py
pychado/orm/pub.py
pychado/orm/sequence.py
pychado/sql/extract_annotation_updates.sql
pychado/sql/extract_curator_comments.sql
pychado/sql/extract_cvterms.sql
pychado/sql/extract_gene_products.sql
pychado/sql/extract_organisms.sql
pychado/sql/extract_public_annotation_updates.sql
pychado/sql/extract_public_curator_comments.sql
pychado/sql/extract_public_gene_products.sql
pychado/sql/extract_public_organisms.sql
pychado/tests/__init__.py
pychado/tests/arguments_tests.py
pychado/tests/dbutils_tests.py
pychado/tests/ddl_tests.py
pychado/tests/io_base_tests.py
pychado/tests/io_direct_tests.py
pychado/tests/io_essentials_tests.py
pychado/tests/io_fasta_tests.py
pychado/tests/io_gaf_tests.py
pychado/tests/io_gff_tests.py
pychado/tests/io_ontology_tests.py
pychado/tests/orm_tests.py
pychado/tests/queries_tests.py
pychado/tests/tasks_tests.py
pychado/tests/utils_tests.py
pychado/tests/data/dbutils_create_table_command.sql
pychado/tests/data/dbutils_example_schema.sql
pychado/tests/data/dbutils_species_table.csv
pychado/tests/data/dbutils_test_result.csv
pychado/tests/data/dbutils_test_result.json
pychado/tests/data/fasta_only.fa
pychado/tests/data/gaf_records.gaf
pychado/tests/data/gff_header.gff3
pychado/tests/data/gff_line.gff3
pychado/tests/data/gff_with_fasta.gff3
pychado/tests/data/gff_without_fasta.gff3
pychado/tests/data/io_obo_example.obo
chado_tools-0.2.14.dist-info/AUTHORS
chado_tools-0.2.14.dist-info/LICENSE
chado_tools-0.2.14.dist-info/METADATA
chado_tools-0.2.14.dist-info/WHEEL
chado_tools-0.2.14.dist-info/entry_points.txt
chado_tools-0.2.14.dist-info/top_level.txt
chado_tools-0.2.14.dist-info/RECORD
