Metadata-Version: 2.1
Name: chado-tools
Version: 0.2.14
Summary: Tools to access CHADO databases
Home-page: https://github.com/sanger-pathogens/chado-tools/
Author: Christoph Puethe
Author-email: path-help@sanger.ac.uk
License: GPLv3
Platform: UNKNOWN
Classifier: Programming Language :: Python :: 3 :: Only
Classifier: License :: OSI Approved :: GNU General Public License v3 (GPLv3)
Classifier: Operating System :: OS Independent
Classifier: Topic :: Scientific/Engineering :: Bio-Informatics
Classifier: Development Status :: 3 - Alpha
Requires-Dist: sqlalchemy (>=1.3.3)
Requires-Dist: sqlalchemy-utils (>=0.34.0)
Requires-Dist: psycopg2 (>=2.7.6)
Requires-Dist: pyyaml (>=5.1)
Requires-Dist: pronto (>=0.11.0)
Requires-Dist: gffutils (>=0.9)
Requires-Dist: biopython (>=1.73)
